{"version": "Latest", "lang_code": "it-IT", "language": "Italiano", "fish": {"128": {"en_name": "Pufferfish", "name": "Pesce palla", "time_ranges": [[1200, 1600]], "weather": ["sunny"], "min_level": 1, "max_depth": 4, "spawn_multi": 0.3, "depth_multi": 0.5, "id": 128, "locations": [{"key": "Beach", "variation": -1, "variation_orig": -1, "name": "Spiaggia di Pelican", "season": "summer"}, {"key": "IslandSouth", "variation": -1, "variation_orig": -1, "name": "Isola Zenzero south", "season": "spring"}, {"key": "IslandSouth", "variation": -1, "variation_orig": -1, "name": "Isola Zenzero south", "season": "summer"}, {"key": "IslandSouth", "variation": -1, "variation_orig": -1, "name": "Isola Zenzero south", "season": "fall"}, {"key": "IslandSouth", "variation": -1, "variation_orig": -1, "name": "Isola Zenzero south", "season": "winter"}, {"key": "IslandWest", "variation": 1, "variation_orig": 1, "name": "Isola Zenzero west (ocean)", "season": "spring"}, {"key": "IslandWest", "variation": 1, "variation_orig": 1, "name": "Isola Zenzero west (ocean)", "season": "summer"}, {"key": "IslandWest", "variation": 1, "variation_orig": 1, "name": "Isola Zenzero west (ocean)", "season": "fall"}, {"key": "IslandWest", "variation": 1, "variation_orig": 1, "name": "Isola Zenzero west (ocean)", "season": "winter"}, {"key": "IslandSouthEast", "variation": -1, "variation_orig": -1, "name": "Isola Zenzero southeast", "season": "spring"}, {"key": "IslandSouthEast", "variation": -1, "variation_orig": -1, "name": "Isola Zenzero southeast", "season": "summer"}, {"key": "IslandSouthEast", "variation": -1, "variation_orig": -1, "name": "Isola Zenzero southeast", "season": "fall"}, {"key": "IslandSouthEast", "variation": -1, "variation_orig": -1, "name": "Isola Zenzero southeast", "season": "winter"}, {"key": "IslandSouthEastCave", "variation": -1, "variation_orig": -1, "name": "Pirate Cove", "season": "spring"}, {"key": "IslandSouthEastCave", "variation": -1, "variation_orig": -1, "name": "Pirate Cove", "season": "summer"}, {"key": "IslandSouthEastCave", "variation": -1, "variation_orig": -1, "name": "Pirate Cove", "season": "fall"}, {"key": "IslandSouthEastCave", "variation": -1, "variation_orig": -1, "name": "Pirate Cove", "season": "winter"}]}, "129": {"en_name": "Anchovy", "name": "Acciuga", "time_ranges": [[600, 2600]], "weather": ["sunny", "rainy"], "min_level": 1, "max_depth": 1, "spawn_multi": 0.25, "depth_multi": 0.3, "id": 129, "locations": [{"key": "Beach", "variation": -1, "variation_orig": -1, "name": "Spiaggia di Pelican", "season": "spring"}, {"key": "Beach", "variation": -1, "variation_orig": -1, "name": "Spiaggia di Pelican", "season": "fall"}]}, "130": {"en_name": "Tuna", "name": "Tonno", "time_ranges": [[600, 1900]], "weather": ["sunny", "rainy"], "min_level": 12, "max_depth": 3, "spawn_multi": 0.15, "depth_multi": 0.55, "id": 130, "locations": [{"key": "Beach", "variation": -1, "variation_orig": -1, "name": "Spiaggia di Pelican", "season": "summer"}, {"key": "Beach", "variation": -1, "variation_orig": -1, "name": "Spiaggia di Pelican", "season": "winter"}, {"key": "IslandSouth", "variation": -1, "variation_orig": -1, "name": "Isola Zenzero south", "season": "spring"}, {"key": "IslandSouth", "variation": -1, "variation_orig": -1, "name": "Isola Zenzero south", "season": "summer"}, {"key": "IslandSouth", "variation": -1, "variation_orig": -1, "name": "Isola Zenzero south", "season": "fall"}, {"key": "IslandSouth", "variation": -1, "variation_orig": -1, "name": "Isola Zenzero south", "season": "winter"}, {"key": "IslandWest", "variation": 1, "variation_orig": 1, "name": "Isola Zenzero west (ocean)", "season": "spring"}, {"key": "IslandWest", "variation": 1, "variation_orig": 1, "name": "Isola Zenzero west (ocean)", "season": "summer"}, {"key": "IslandWest", "variation": 1, "variation_orig": 1, "name": "Isola Zenzero west (ocean)", "season": "fall"}, {"key": "IslandWest", "variation": 1, "variation_orig": 1, "name": "Isola Zenzero west (ocean)", "season": "winter"}, {"key": "IslandSouthEast", "variation": -1, "variation_orig": -1, "name": "Isola Zenzero southeast", "season": "spring"}, {"key": "IslandSouthEast", "variation": -1, "variation_orig": -1, "name": "Isola Zenzero southeast", "season": "summer"}, {"key": "IslandSouthEast", "variation": -1, "variation_orig": -1, "name": "Isola Zenzero southeast", "season": "fall"}, {"key": "IslandSouthEast", "variation": -1, "variation_orig": -1, "name": "Isola Zenzero southeast", "season": "winter"}, {"key": "IslandSouthEastCave", "variation": -1, "variation_orig": -1, "name": "Pirate Cove", "season": "spring"}, {"key": "IslandSouthEastCave", "variation": -1, "variation_orig": -1, "name": "Pirate Cove", "season": "summer"}, {"key": "IslandSouthEastCave", "variation": -1, "variation_orig": -1, "name": "Pirate Cove", "season": "fall"}, {"key": "IslandSouthEastCave", "variation": -1, "variation_orig": -1, "name": "Pirate Cove", "season": "winter"}, {"key": "IslandSecret", "variation": -1, "variation_orig": -1, "name": "Isola Zenzero secret location", "season": "spring"}, {"key": "IslandSecret", "variation": -1, "variation_orig": -1, "name": "Isola Zenzero secret location", "season": "summer"}, {"key": "IslandSecret", "variation": -1, "variation_orig": -1, "name": "Isola Zenzero secret location", "season": "fall"}, {"key": "IslandSecret", "variation": -1, "variation_orig": -1, "name": "Isola Zenzero secret location", "season": "winter"}]}, "131": {"en_name": "Sardine", "name": "Sardina", "time_ranges": [[600, 1900]], "weather": ["sunny", "rainy"], "min_level": 1, "max_depth": 1, "spawn_multi": 0.65, "depth_multi": 0.1, "id": 131, "locations": [{"key": "Beach", "variation": -1, "variation_orig": -1, "name": "Spiaggia di Pelican", "season": "spring"}, {"key": "Beach", "variation": -1, "variation_orig": -1, "name": "Spiaggia di Pelican", "season": "fall"}, {"key": "Beach", "variation": -1, "variation_orig": -1, "name": "Spiaggia di Pelican", "season": "winter"}]}, "132": {"en_name": "Bream", "name": "Abramide", "time_ranges": [[1800, 2600]], "weather": ["sunny", "rainy"], "min_level": 12, "max_depth": 1, "spawn_multi": 0.45, "depth_multi": 0.1, "id": 132, "locations": [{"key": "Forest", "variation": 0, "variation_orig": 0, "name": "Foresta Linfabrace (river)", "season": "spring"}, {"key": "Forest", "variation": 0, "variation_orig": 0, "name": "Foresta Linfabrace (river)", "season": "summer"}, {"key": "Forest", "variation": 0, "variation_orig": 0, "name": "Foresta Linfabrace (river)", "season": "fall"}, {"key": "Forest", "variation": 0, "variation_orig": 0, "name": "Foresta Linfabrace (river)", "season": "winter"}, {"key": "Town", "variation": -1, "variation_orig": -1, "name": "Pelican Town", "season": "spring"}, {"key": "Town", "variation": -1, "variation_orig": -1, "name": "Pelican Town", "season": "summer"}, {"key": "Town", "variation": -1, "variation_orig": -1, "name": "Pelican Town", "season": "fall"}, {"key": "Town", "variation": -1, "variation_orig": -1, "name": "Pelican Town", "season": "winter"}]}, "136": {"en_name": "Largemouth Bass", "name": "Boccalone", "time_ranges": [[600, 1900]], "weather": ["sunny", "rainy"], "min_level": 11, "max_depth": 3, "spawn_multi": 0.4, "depth_multi": 0.2, "id": 136, "locations": [{"key": "Mountain", "variation": -1, "variation_orig": -1, "name": "Lago montano", "season": "spring"}, {"key": "Mountain", "variation": -1, "variation_orig": -1, "name": "Lago montano", "season": "summer"}, {"key": "Mountain", "variation": -1, "variation_orig": -1, "name": "Lago montano", "season": "fall"}, {"key": "Mountain", "variation": -1, "variation_orig": -1, "name": "Lago montano", "season": "winter"}, {"key": "Backwoods", "variation": -1, "variation_orig": -1, "name": "Boschi sul retro", "season": "spring"}, {"key": "Backwoods", "variation": -1, "variation_orig": -1, "name": "Boschi sul retro", "season": "summer"}, {"key": "Backwoods", "variation": -1, "variation_orig": -1, "name": "Boschi sul retro", "season": "fall"}, {"key": "Backwoods", "variation": -1, "variation_orig": -1, "name": "Boschi sul retro", "season": "winter"}]}, "137": {"en_name": "Smallmouth Bass", "name": "Boccalino", "time_ranges": [[600, 2600]], "weather": ["sunny", "rainy"], "min_level": 12, "max_depth": 1, "spawn_multi": 0.45, "depth_multi": 0.1, "id": 137, "locations": [{"key": "Forest", "variation": 1, "variation_orig": 1, "name": "Foresta Linfabrace (pond)", "season": "spring"}, {"key": "Forest", "variation": 1, "variation_orig": 1, "name": "Foresta Linfabrace (pond)", "season": "fall"}, {"key": "Town", "variation": -1, "variation_orig": -1, "name": "Pelican Town", "season": "spring"}, {"key": "Town", "variation": -1, "variation_orig": -1, "name": "Pelican Town", "season": "fall"}]}, "138": {"en_name": "Rainbow Trout", "name": "Trota arcobaleno", "time_ranges": [[600, 1900]], "weather": ["sunny"], "min_level": 10, "max_depth": 2, "spawn_multi": 0.35, "depth_multi": 0.3, "id": 138, "locations": [{"key": "Forest", "variation": 0, "variation_orig": 0, "name": "Foresta Linfabrace (river)", "season": "summer"}, {"key": "Town", "variation": -1, "variation_orig": -1, "name": "Pelican Town", "season": "summer"}, {"key": "Mountain", "variation": -1, "variation_orig": -1, "name": "Lago montano", "season": "summer"}, {"key": "Backwoods", "variation": -1, "variation_orig": -1, "name": "Boschi sul retro", "season": "summer"}]}, "139": {"en_name": "Salmon", "name": "Salmone", "time_ranges": [[600, 1900]], "weather": ["sunny", "rainy"], "min_level": 24, "max_depth": 3, "spawn_multi": 0.4, "depth_multi": 0.2, "id": 139, "locations": [{"key": "Forest", "variation": 0, "variation_orig": 0, "name": "Foresta Linfabrace (river)", "season": "fall"}, {"key": "Town", "variation": -1, "variation_orig": -1, "name": "Pelican Town", "season": "fall"}]}, "140": {"en_name": "Walleye", "name": "Walleye", "time_ranges": [[1200, 2600]], "weather": ["rainy"], "min_level": 10, "max_depth": 2, "spawn_multi": 0.4, "depth_multi": 0.15, "id": 140, "locations": [{"key": "Forest", "variation": 0, "variation_orig": -1, "name": "Foresta Linfabrace (river)", "season": "fall"}, {"key": "Forest", "variation": 1, "variation_orig": -1, "name": "Foresta Linfabrace (pond)", "season": "fall"}, {"key": "Forest", "variation": 0, "variation_orig": -1, "name": "Foresta Linfabrace (river)", "season": "winter"}, {"key": "Forest", "variation": 1, "variation_orig": -1, "name": "Foresta Linfabrace (pond)", "season": "winter"}, {"key": "Town", "variation": -1, "variation_orig": -1, "name": "Pelican Town", "season": "fall"}, {"key": "Town", "variation": -1, "variation_orig": -1, "name": "Pelican Town", "season": "winter"}, {"key": "Mountain", "variation": -1, "variation_orig": -1, "name": "Lago montano", "season": "fall"}, {"key": "Mountain", "variation": -1, "variation_orig": -1, "name": "Lago montano", "season": "winter"}, {"key": "Backwoods", "variation": -1, "variation_orig": -1, "name": "Boschi sul retro", "season": "fall"}, {"key": "Backwoods", "variation": -1, "variation_orig": -1, "name": "Boschi sul retro", "season": "winter"}]}, "141": {"en_name": "Perch", "name": "Pesce persico", "time_ranges": [[600, 2600]], "weather": ["sunny", "rainy"], "min_level": 10, "max_depth": 1, "spawn_multi": 0.45, "depth_multi": 0.1, "id": 141, "locations": [{"key": "Forest", "variation": 0, "variation_orig": -1, "name": "Foresta Linfabrace (river)", "season": "winter"}, {"key": "Forest", "variation": 1, "variation_orig": -1, "name": "Foresta Linfabrace (pond)", "season": "winter"}, {"key": "Town", "variation": -1, "variation_orig": -1, "name": "Pelican Town", "season": "winter"}, {"key": "Mountain", "variation": -1, "variation_orig": -1, "name": "Lago montano", "season": "winter"}, {"key": "Backwoods", "variation": -1, "variation_orig": -1, "name": "Boschi sul retro", "season": "winter"}]}, "142": {"en_name": "Carp", "name": "Carpa", "time_ranges": [[600, 2600]], "weather": ["sunny", "rainy"], "min_level": 15, "max_depth": 1, "spawn_multi": 0.45, "depth_multi": 0.1, "id": 142, "locations": [{"key": "Mountain", "variation": -1, "variation_orig": -1, "name": "Lago montano", "season": "spring"}, {"key": "Mountain", "variation": -1, "variation_orig": -1, "name": "Lago montano", "season": "summer"}, {"key": "Mountain", "variation": -1, "variation_orig": -1, "name": "Lago montano", "season": "fall"}, {"key": "Backwoods", "variation": -1, "variation_orig": -1, "name": "Boschi sul retro", "season": "spring"}, {"key": "Backwoods", "variation": -1, "variation_orig": -1, "name": "Boschi sul retro", "season": "summer"}, {"key": "Backwoods", "variation": -1, "variation_orig": -1, "name": "Boschi sul retro", "season": "fall"}, {"key": "Woods", "variation": -1, "variation_orig": -1, "name": "Boschi segreti", "season": "spring"}, {"key": "Woods", "variation": -1, "variation_orig": -1, "name": "Boschi segreti", "season": "summer"}, {"key": "Woods", "variation": -1, "variation_orig": -1, "name": "Boschi segreti", "season": "fall"}, {"key": "Woods", "variation": -1, "variation_orig": -1, "name": "Boschi segreti", "season": "winter"}, {"key": "Sewer", "variation": -1, "variation_orig": -1, "name": "Fogne", "season": "spring"}, {"key": "Sewer", "variation": -1, "variation_orig": -1, "name": "Fogne", "season": "summer"}, {"key": "Sewer", "variation": -1, "variation_orig": -1, "name": "Fogne", "season": "fall"}, {"key": "Sewer", "variation": -1, "variation_orig": -1, "name": "Fogne", "season": "winter"}, {"key": "BugLand", "variation": -1, "variation_orig": -1, "name": "Mutant Bug Lair", "season": "spring"}, {"key": "BugLand", "variation": -1, "variation_orig": -1, "name": "Mutant Bug Lair", "season": "summer"}, {"key": "BugLand", "variation": -1, "variation_orig": -1, "name": "Mutant Bug Lair", "season": "fall"}, {"key": "BugLand", "variation": -1, "variation_orig": -1, "name": "Mutant Bug Lair", "season": "winter"}]}, "143": {"en_name": "Catfish", "name": "Pesce gatto", "time_ranges": [[600, 2400]], "weather": ["rainy"], "min_level": 12, "max_depth": 4, "spawn_multi": 0.4, "depth_multi": 0.1, "id": 143, "locations": [{"key": "Forest", "variation": 0, "variation_orig": 0, "name": "Foresta Linfabrace (river)", "season": "spring"}, {"key": "Forest", "variation": 0, "variation_orig": 0, "name": "Foresta Linfabrace (river)", "season": "fall"}, {"key": "Forest", "variation": 0, "variation_orig": 0, "name": "Foresta Linfabrace (river)", "season": "winter"}, {"key": "Town", "variation": -1, "variation_orig": -1, "name": "Pelican Town", "season": "spring"}, {"key": "Town", "variation": -1, "variation_orig": -1, "name": "Pelican Town", "season": "fall"}, {"key": "Town", "variation": -1, "variation_orig": -1, "name": "Pelican Town", "season": "winter"}, {"key": "Woods", "variation": -1, "variation_orig": -1, "name": "Boschi segreti", "season": "spring"}, {"key": "Woods", "variation": -1, "variation_orig": -1, "name": "Boschi segreti", "season": "summer"}, {"key": "Woods", "variation": -1, "variation_orig": -1, "name": "Boschi segreti", "season": "fall"}, {"key": "Woods", "variation": -1, "variation_orig": -1, "name": "Boschi segreti", "season": "winter"}, {"key": "WitchSwamp", "variation": -1, "variation_orig": -1, "name": "Witch's Swamp", "season": "spring"}, {"key": "WitchSwamp", "variation": -1, "variation_orig": -1, "name": "Witch's Swamp", "season": "summer"}, {"key": "WitchSwamp", "variation": -1, "variation_orig": -1, "name": "Witch's Swamp", "season": "fall"}, {"key": "WitchSwamp", "variation": -1, "variation_orig": -1, "name": "Witch's Swamp", "season": "winter"}]}, "144": {"en_name": "Pike", "name": "Luccio", "time_ranges": [[600, 2600]], "weather": ["sunny", "rainy"], "min_level": 15, "max_depth": 3, "spawn_multi": 0.4, "depth_multi": 0.15, "id": 144, "locations": [{"key": "Forest", "variation": 0, "variation_orig": -1, "name": "Foresta Linfabrace (river)", "season": "summer"}, {"key": "Forest", "variation": 1, "variation_orig": -1, "name": "Foresta Linfabrace (pond)", "season": "summer"}, {"key": "Forest", "variation": 0, "variation_orig": -1, "name": "Foresta Linfabrace (river)", "season": "winter"}, {"key": "Forest", "variation": 1, "variation_orig": -1, "name": "Foresta Linfabrace (pond)", "season": "winter"}, {"key": "Town", "variation": -1, "variation_orig": -1, "name": "Pelican Town", "season": "summer"}, {"key": "Town", "variation": -1, "variation_orig": -1, "name": "Pelican Town", "season": "winter"}]}, "145": {"en_name": "Sunfish", "name": "Persico sole", "time_ranges": [[600, 1900]], "weather": ["sunny"], "min_level": 5, "max_depth": 1, "spawn_multi": 0.45, "depth_multi": 0.1, "id": 145, "locations": [{"key": "Forest", "variation": 0, "variation_orig": 0, "name": "Foresta Linfabrace (river)", "season": "spring"}, {"key": "Forest", "variation": 0, "variation_orig": 0, "name": "Foresta Linfabrace (river)", "season": "summer"}, {"key": "Town", "variation": -1, "variation_orig": -1, "name": "Pelican Town", "season": "spring"}, {"key": "Town", "variation": -1, "variation_orig": -1, "name": "Pelican Town", "season": "summer"}]}, "146": {"en_name": "Red Mullet", "name": "Triglia", "time_ranges": [[600, 1900]], "weather": ["sunny", "rainy"], "min_level": 8, "max_depth": 2, "spawn_multi": 0.4, "depth_multi": 0.15, "id": 146, "locations": [{"key": "Beach", "variation": -1, "variation_orig": -1, "name": "Spiaggia di Pelican", "season": "summer"}, {"key": "Beach", "variation": -1, "variation_orig": -1, "name": "Spiaggia di Pelican", "season": "winter"}, {"key": "IslandSecret", "variation": -1, "variation_orig": -1, "name": "Isola Zenzero secret location", "season": "spring"}, {"key": "IslandSecret", "variation": -1, "variation_orig": -1, "name": "Isola Zenzero secret location", "season": "summer"}, {"key": "IslandSecret", "variation": -1, "variation_orig": -1, "name": "Isola Zenzero secret location", "season": "fall"}, {"key": "IslandSecret", "variation": -1, "variation_orig": -1, "name": "Isola Zenzero secret location", "season": "winter"}]}, "147": {"en_name": "Herring", "name": "Aringa", "time_ranges": [[600, 2600]], "weather": ["sunny", "rainy"], "min_level": 8, "max_depth": 1, "spawn_multi": 0.45, "depth_multi": 0.1, "id": 147, "locations": [{"key": "Beach", "variation": -1, "variation_orig": -1, "name": "Spiaggia di Pelican", "season": "spring"}, {"key": "Beach", "variation": -1, "variation_orig": -1, "name": "Spiaggia di Pelican", "season": "winter"}]}, "148": {"en_name": "Eel", "name": "Anguilla", "time_ranges": [[1600, 2600]], "weather": ["rainy"], "min_level": 12, "max_depth": 3, "spawn_multi": 0.55, "depth_multi": 0.1, "id": 148, "locations": [{"key": "Beach", "variation": -1, "variation_orig": -1, "name": "Spiaggia di Pelican", "season": "spring"}, {"key": "Beach", "variation": -1, "variation_orig": -1, "name": "Spiaggia di Pelican", "season": "fall"}]}, "149": {"en_name": "Octopus", "name": "Piovra", "time_ranges": [[600, 1300]], "weather": ["sunny", "rainy"], "min_level": 12, "max_depth": 5, "spawn_multi": 0.1, "depth_multi": 0.08, "id": 149, "locations": [{"key": "Beach", "variation": -1, "variation_orig": -1, "name": "Spiaggia di Pelican", "season": "summer"}, {"key": "IslandWest", "variation": 1, "variation_orig": 1, "name": "Isola Zenzero west (ocean)", "season": "spring"}, {"key": "IslandWest", "variation": 1, "variation_orig": 1, "name": "Isola Zenzero west (ocean)", "season": "summer"}, {"key": "IslandWest", "variation": 1, "variation_orig": 1, "name": "Isola Zenzero west (ocean)", "season": "fall"}, {"key": "IslandWest", "variation": 1, "variation_orig": 1, "name": "Isola Zenzero west (ocean)", "season": "winter"}]}, "150": {"en_name": "Red Snapper", "name": "Dentice rosso", "time_ranges": [[600, 1900]], "weather": ["rainy"], "min_level": 8, "max_depth": 2, "spawn_multi": 0.45, "depth_multi": 0.1, "id": 150, "locations": [{"key": "Beach", "variation": -1, "variation_orig": -1, "name": "Spiaggia di Pelican", "season": "summer"}, {"key": "Beach", "variation": -1, "variation_orig": -1, "name": "Spiaggia di Pelican", "season": "fall"}, {"key": "Beach", "variation": -1, "variation_orig": -1, "name": "Spiaggia di Pelican", "season": "winter"}]}, "151": {"en_name": "Squid", "name": "Calamaro", "time_ranges": [[1800, 2600]], "weather": ["sunny", "rainy"], "min_level": 12, "max_depth": 3, "spawn_multi": 0.35, "depth_multi": 0.3, "id": 151, "locations": [{"key": "Beach", "variation": -1, "variation_orig": -1, "name": "Spiaggia di Pelican", "season": "winter"}, {"key": "IslandSecret", "variation": -1, "variation_orig": -1, "name": "Isola Zenzero secret location", "season": "spring"}, {"key": "IslandSecret", "variation": -1, "variation_orig": -1, "name": "Isola Zenzero secret location", "season": "summer"}, {"key": "IslandSecret", "variation": -1, "variation_orig": -1, "name": "Isola Zenzero secret location", "season": "fall"}, {"key": "IslandSecret", "variation": -1, "variation_orig": -1, "name": "Isola Zenzero secret location", "season": "winter"}]}, "152": {"en_name": "Seaweed", "name": "Alga marina", "time_ranges": [[600, 2600]], "weather": ["sunny", "rainy"], "min_level": 5, "max_depth": 0, "spawn_multi": 0.3, "depth_multi": 0.0, "id": 152, "locations": [{"key": "Beach", "variation": -1, "variation_orig": -1, "name": "Spiaggia di Pelican", "season": "spring"}, {"key": "Beach", "variation": -1, "variation_orig": -1, "name": "Spiaggia di Pelican", "season": "summer"}, {"key": "Beach", "variation": -1, "variation_orig": -1, "name": "Spiaggia di Pelican", "season": "fall"}, {"key": "Beach", "variation": -1, "variation_orig": -1, "name": "Spiaggia di Pelican", "season": "winter"}]}, "153": {"en_name": "Green Algae", "name": "Alghetta verde", "time_ranges": [[600, 2600]], "weather": ["sunny", "rainy"], "min_level": 5, "max_depth": 0, "spawn_multi": 0.3, "depth_multi": 0.0, "id": 153, "locations": [{"key": "UndergroundMine", "variation": -1, "variation_orig": -1, "name": "Miniere", "season": "spring"}, {"key": "UndergroundMine", "variation": -1, "variation_orig": -1, "name": "Miniere", "season": "summer"}, {"key": "UndergroundMine", "variation": -1, "variation_orig": -1, "name": "Miniere", "season": "fall"}, {"key": "UndergroundMine", "variation": -1, "variation_orig": -1, "name": "Miniere", "season": "winter"}, {"key": "Desert", "variation": -1, "variation_orig": -1, "name": "Deserto di Calico", "season": "spring"}, {"key": "Desert", "variation": -1, "variation_orig": -1, "name": "Deserto di Calico", "season": "summer"}, {"key": "Desert", "variation": -1, "variation_orig": -1, "name": "Deserto di Calico", "season": "fall"}, {"key": "Desert", "variation": -1, "variation_orig": -1, "name": "Deserto di Calico", "season": "winter"}, {"key": "Forest", "variation": 0, "variation_orig": -1, "name": "Foresta Linfabrace (river)", "season": "spring"}, {"key": "Forest", "variation": 1, "variation_orig": -1, "name": "Foresta Linfabrace (pond)", "season": "spring"}, {"key": "Forest", "variation": 0, "variation_orig": -1, "name": "Foresta Linfabrace (river)", "season": "summer"}, {"key": "Forest", "variation": 1, "variation_orig": -1, "name": "Foresta Linfabrace (pond)", "season": "summer"}, {"key": "Forest", "variation": 0, "variation_orig": -1, "name": "Foresta Linfabrace (river)", "season": "fall"}, {"key": "Forest", "variation": 1, "variation_orig": -1, "name": "Foresta Linfabrace (pond)", "season": "fall"}, {"key": "Forest", "variation": 0, "variation_orig": -1, "name": "Foresta Linfabrace (river)", "season": "winter"}, {"key": "Forest", "variation": 1, "variation_orig": -1, "name": "Foresta Linfabrace (pond)", "season": "winter"}, {"key": "Town", "variation": -1, "variation_orig": -1, "name": "Pelican Town", "season": "spring"}, {"key": "Town", "variation": -1, "variation_orig": -1, "name": "Pelican Town", "season": "summer"}, {"key": "Town", "variation": -1, "variation_orig": -1, "name": "Pelican Town", "season": "fall"}, {"key": "Town", "variation": -1, "variation_orig": -1, "name": "Pelican Town", "season": "winter"}, {"key": "Mountain", "variation": -1, "variation_orig": -1, "name": "Lago montano", "season": "spring"}, {"key": "Mountain", "variation": -1, "variation_orig": -1, "name": "Lago montano", "season": "summer"}, {"key": "Mountain", "variation": -1, "variation_orig": -1, "name": "Lago montano", "season": "fall"}, {"key": "Mountain", "variation": -1, "variation_orig": -1, "name": "Lago montano", "season": "winter"}, {"key": "Backwoods", "variation": -1, "variation_orig": -1, "name": "Boschi sul retro", "season": "spring"}, {"key": "Backwoods", "variation": -1, "variation_orig": -1, "name": "Boschi sul retro", "season": "summer"}, {"key": "Backwoods", "variation": -1, "variation_orig": -1, "name": "Boschi sul retro", "season": "fall"}, {"key": "Backwoods", "variation": -1, "variation_orig": -1, "name": "Boschi sul retro", "season": "winter"}, {"key": "Sewer", "variation": -1, "variation_orig": -1, "name": "Fogne", "season": "spring"}, {"key": "Sewer", "variation": -1, "variation_orig": -1, "name": "Fogne", "season": "summer"}, {"key": "Sewer", "variation": -1, "variation_orig": -1, "name": "Fogne", "season": "fall"}, {"key": "Sewer", "variation": -1, "variation_orig": -1, "name": "Fogne", "season": "winter"}, {"key": "BugLand", "variation": -1, "variation_orig": -1, "name": "Mutant Bug Lair", "season": "spring"}, {"key": "BugLand", "variation": -1, "variation_orig": -1, "name": "Mutant Bug Lair", "season": "summer"}, {"key": "BugLand", "variation": -1, "variation_orig": -1, "name": "Mutant Bug Lair", "season": "fall"}, {"key": "BugLand", "variation": -1, "variation_orig": -1, "name": "Mutant Bug Lair", "season": "winter"}, {"key": "WitchSwamp", "variation": -1, "variation_orig": -1, "name": "Witch's Swamp", "season": "spring"}, {"key": "WitchSwamp", "variation": -1, "variation_orig": -1, "name": "Witch's Swamp", "season": "summer"}, {"key": "WitchSwamp", "variation": -1, "variation_orig": -1, "name": "Witch's Swamp", "season": "fall"}, {"key": "WitchSwamp", "variation": -1, "variation_orig": -1, "name": "Witch's Swamp", "season": "winter"}]}, "154": {"en_name": "Sea Cucumber", "name": "Cetriolo di mare", "time_ranges": [[600, 1900]], "weather": ["sunny", "rainy"], "min_level": 3, "max_depth": 3, "spawn_multi": 0.25, "depth_multi": 0.25, "id": 154, "locations": [{"key": "Beach", "variation": -1, "variation_orig": -1, "name": "Spiaggia di Pelican", "season": "fall"}, {"key": "Beach", "variation": -1, "variation_orig": -1, "name": "Spiaggia di Pelican", "season": "winter"}]}, "155": {"en_name": "Super Cucumber", "name": "Supercetriolo", "time_ranges": [[1800, 2600]], "weather": ["sunny", "rainy"], "min_level": 12, "max_depth": 4, "spawn_multi": 0.1, "depth_multi": 0.25, "id": 155, "locations": [{"key": "Beach", "variation": -1, "variation_orig": -1, "name": "Spiaggia di Pelican", "season": "summer"}, {"key": "Beach", "variation": -1, "variation_orig": -1, "name": "Spiaggia di Pelican", "season": "fall"}, {"key": "IslandSouth", "variation": -1, "variation_orig": -1, "name": "Isola Zenzero south", "season": "spring"}, {"key": "IslandSouth", "variation": -1, "variation_orig": -1, "name": "Isola Zenzero south", "season": "summer"}, {"key": "IslandSouth", "variation": -1, "variation_orig": -1, "name": "Isola Zenzero south", "season": "fall"}, {"key": "IslandSouth", "variation": -1, "variation_orig": -1, "name": "Isola Zenzero south", "season": "winter"}, {"key": "IslandWest", "variation": 1, "variation_orig": 1, "name": "Isola Zenzero west (ocean)", "season": "spring"}, {"key": "IslandWest", "variation": 1, "variation_orig": 1, "name": "Isola Zenzero west (ocean)", "season": "summer"}, {"key": "IslandWest", "variation": 1, "variation_orig": 1, "name": "Isola Zenzero west (ocean)", "season": "fall"}, {"key": "IslandWest", "variation": 1, "variation_orig": 1, "name": "Isola Zenzero west (ocean)", "season": "winter"}, {"key": "IslandSouthEast", "variation": -1, "variation_orig": -1, "name": "Isola Zenzero southeast", "season": "spring"}, {"key": "IslandSouthEast", "variation": -1, "variation_orig": -1, "name": "Isola Zenzero southeast", "season": "summer"}, {"key": "IslandSouthEast", "variation": -1, "variation_orig": -1, "name": "Isola Zenzero southeast", "season": "fall"}, {"key": "IslandSouthEast", "variation": -1, "variation_orig": -1, "name": "Isola Zenzero southeast", "season": "winter"}, {"key": "IslandSouthEastCave", "variation": -1, "variation_orig": -1, "name": "Pirate Cove", "season": "spring"}, {"key": "IslandSouthEastCave", "variation": -1, "variation_orig": -1, "name": "Pirate Cove", "season": "summer"}, {"key": "IslandSouthEastCave", "variation": -1, "variation_orig": -1, "name": "Pirate Cove", "season": "fall"}, {"key": "IslandSouthEastCave", "variation": -1, "variation_orig": -1, "name": "Pirate Cove", "season": "winter"}, {"key": "IslandSecret", "variation": -1, "variation_orig": -1, "name": "Isola Zenzero secret location", "season": "spring"}, {"key": "IslandSecret", "variation": -1, "variation_orig": -1, "name": "Isola Zenzero secret location", "season": "summer"}, {"key": "IslandSecret", "variation": -1, "variation_orig": -1, "name": "Isola Zenzero secret location", "season": "fall"}, {"key": "IslandSecret", "variation": -1, "variation_orig": -1, "name": "Isola Zenzero secret location", "season": "winter"}]}, "156": {"en_name": "Ghostfish", "name": "Pesce fantasma", "time_ranges": [[600, 2600]], "weather": ["sunny", "rainy"], "min_level": 10, "max_depth": 2, "spawn_multi": 0.3, "depth_multi": 0.3, "id": 156, "locations": [{"key": "UndergroundMine", "variation": -1, "variation_orig": -1, "name": "Miniere", "season": "spring"}, {"key": "UndergroundMine", "variation": -1, "variation_orig": -1, "name": "Miniere", "season": "summer"}, {"key": "UndergroundMine", "variation": -1, "variation_orig": -1, "name": "Miniere", "season": "fall"}, {"key": "UndergroundMine", "variation": -1, "variation_orig": -1, "name": "Miniere", "season": "winter"}]}, "157": {"en_name": "White Algae", "name": "Alghetta bianca", "time_ranges": [[600, 2600]], "weather": ["sunny", "rainy"], "min_level": 5, "max_depth": 0, "spawn_multi": 0.3, "depth_multi": 0.0, "id": 157, "locations": [{"key": "UndergroundMine", "variation": -1, "variation_orig": -1, "name": "Miniere", "season": "spring"}, {"key": "UndergroundMine", "variation": -1, "variation_orig": -1, "name": "Miniere", "season": "summer"}, {"key": "UndergroundMine", "variation": -1, "variation_orig": -1, "name": "Miniere", "season": "fall"}, {"key": "UndergroundMine", "variation": -1, "variation_orig": -1, "name": "Miniere", "season": "winter"}, {"key": "Sewer", "variation": -1, "variation_orig": -1, "name": "Fogne", "season": "spring"}, {"key": "Sewer", "variation": -1, "variation_orig": -1, "name": "Fogne", "season": "summer"}, {"key": "Sewer", "variation": -1, "variation_orig": -1, "name": "Fogne", "season": "fall"}, {"key": "Sewer", "variation": -1, "variation_orig": -1, "name": "Fogne", "season": "winter"}, {"key": "BugLand", "variation": -1, "variation_orig": -1, "name": "Mutant Bug Lair", "season": "spring"}, {"key": "BugLand", "variation": -1, "variation_orig": -1, "name": "Mutant Bug Lair", "season": "summer"}, {"key": "BugLand", "variation": -1, "variation_orig": -1, "name": "Mutant Bug Lair", "season": "fall"}, {"key": "BugLand", "variation": -1, "variation_orig": -1, "name": "Mutant Bug Lair", "season": "winter"}, {"key": "WitchSwamp", "variation": -1, "variation_orig": -1, "name": "Witch's Swamp", "season": "spring"}, {"key": "WitchSwamp", "variation": -1, "variation_orig": -1, "name": "Witch's Swamp", "season": "summer"}, {"key": "WitchSwamp", "variation": -1, "variation_orig": -1, "name": "Witch's Swamp", "season": "fall"}, {"key": "WitchSwamp", "variation": -1, "variation_orig": -1, "name": "Witch's Swamp", "season": "winter"}]}, "158": {"en_name": "Stonefish", "name": "Pesce pietra", "time_ranges": [[600, 2600]], "weather": ["sunny", "rainy"], "min_level": 15, "max_depth": 2, "spawn_multi": 0.1, "depth_multi": 0.1, "id": 158}, "159": {"en_name": "Crimsonfish", "name": "Pesce cremisi", "time_ranges": [[600, 2000]], "weather": ["sunny", "rainy"], "min_level": 20, "max_depth": 4, "spawn_multi": 0.1, "depth_multi": 0.1, "id": 159}, "160": {"en_name": "Angler", "name": "Rana pescatrice", "time_ranges": [[600, 2600]], "weather": ["sunny", "rainy"], "min_level": 18, "max_depth": 4, "spawn_multi": 0.05, "depth_multi": 0.1, "id": 160}, "161": {"en_name": "Ice Pip", "name": "Ghiacciolo", "time_ranges": [[600, 2600]], "weather": ["sunny", "rainy"], "min_level": 8, "max_depth": 2, "spawn_multi": 0.05, "depth_multi": 0.1, "id": 161}, "162": {"en_name": "Lava Eel", "name": "Anguilla lavica", "time_ranges": [[600, 2600]], "weather": ["sunny", "rainy"], "min_level": 32, "max_depth": 2, "spawn_multi": 0.05, "depth_multi": 0.1, "id": 162}, "163": {"en_name": "Legend", "name": "Leggenda", "time_ranges": [[600, 2000]], "weather": ["rainy"], "min_level": 50, "max_depth": 5, "spawn_multi": 0.0, "depth_multi": 0.1, "id": 163, "locations": [{"key": "Backwoods", "variation": -1, "variation_orig": -1, "name": "Boschi sul retro", "season": "spring"}]}, "775": {"en_name": "Glacierfish", "name": "Pesce ghiacciaio", "time_ranges": [[600, 2000]], "weather": ["sunny"], "min_level": 27, "max_depth": 5, "spawn_multi": 0.0, "depth_multi": 0.02, "id": 775}, "682": {"en_name": "Mutant Carp", "name": "Carpa mutante", "time_ranges": [[600, 2600]], "weather": ["sunny", "rainy"], "min_level": 36, "max_depth": 5, "spawn_multi": 0.0, "depth_multi": 0.02, "id": 682}, "164": {"en_name": "Sandfish", "name": "Pesce delle sabbie", "time_ranges": [[600, 2000]], "weather": ["sunny", "rainy"], "min_level": 8, "max_depth": 1, "spawn_multi": 0.65, "depth_multi": 0.1, "id": 164, "locations": [{"key": "Desert", "variation": -1, "variation_orig": -1, "name": "Deserto di Calico", "season": "spring"}, {"key": "Desert", "variation": -1, "variation_orig": -1, "name": "Deserto di Calico", "season": "summer"}, {"key": "Desert", "variation": -1, "variation_orig": -1, "name": "Deserto di Calico", "season": "fall"}, {"key": "Desert", "variation": -1, "variation_orig": -1, "name": "Deserto di Calico", "season": "winter"}]}, "165": {"en_name": "Scorpion Carp", "name": "Carpa scorpione", "time_ranges": [[600, 2000]], "weather": ["sunny", "rainy"], "min_level": 12, "max_depth": 2, "spawn_multi": 0.15, "depth_multi": 0.1, "id": 165, "locations": [{"key": "Desert", "variation": -1, "variation_orig": -1, "name": "Deserto di Calico", "season": "spring"}, {"key": "Desert", "variation": -1, "variation_orig": -1, "name": "Deserto di Calico", "season": "summer"}, {"key": "Desert", "variation": -1, "variation_orig": -1, "name": "Deserto di Calico", "season": "fall"}, {"key": "Desert", "variation": -1, "variation_orig": -1, "name": "Deserto di Calico", "season": "winter"}]}, "267": {"en_name": "Flounder", "name": "Platessa", "time_ranges": [[600, 2000]], "weather": ["sunny", "rainy"], "min_level": 4, "max_depth": 2, "spawn_multi": 0.15, "depth_multi": 0.05, "id": 267, "locations": [{"key": "Beach", "variation": -1, "variation_orig": -1, "name": "Spiaggia di Pelican", "season": "spring"}, {"key": "Beach", "variation": -1, "variation_orig": -1, "name": "Spiaggia di Pelican", "season": "summer"}, {"key": "IslandSouth", "variation": -1, "variation_orig": -1, "name": "Isola Zenzero south", "season": "spring"}, {"key": "IslandSouth", "variation": -1, "variation_orig": -1, "name": "Isola Zenzero south", "season": "summer"}, {"key": "IslandSouth", "variation": -1, "variation_orig": -1, "name": "Isola Zenzero south", "season": "fall"}, {"key": "IslandSouth", "variation": -1, "variation_orig": -1, "name": "Isola Zenzero south", "season": "winter"}, {"key": "IslandWest", "variation": 1, "variation_orig": 1, "name": "Isola Zenzero west (ocean)", "season": "spring"}, {"key": "IslandWest", "variation": 1, "variation_orig": 1, "name": "Isola Zenzero west (ocean)", "season": "summer"}, {"key": "IslandWest", "variation": 1, "variation_orig": 1, "name": "Isola Zenzero west (ocean)", "season": "fall"}, {"key": "IslandWest", "variation": 1, "variation_orig": 1, "name": "Isola Zenzero west (ocean)", "season": "winter"}, {"key": "IslandSouthEast", "variation": -1, "variation_orig": -1, "name": "Isola Zenzero southeast", "season": "spring"}, {"key": "IslandSouthEast", "variation": -1, "variation_orig": -1, "name": "Isola Zenzero southeast", "season": "summer"}, {"key": "IslandSouthEast", "variation": -1, "variation_orig": -1, "name": "Isola Zenzero southeast", "season": "fall"}, {"key": "IslandSouthEast", "variation": -1, "variation_orig": -1, "name": "Isola Zenzero southeast", "season": "winter"}, {"key": "IslandSouthEastCave", "variation": -1, "variation_orig": -1, "name": "Pirate Cove", "season": "spring"}, {"key": "IslandSouthEastCave", "variation": -1, "variation_orig": -1, "name": "Pirate Cove", "season": "summer"}, {"key": "IslandSouthEastCave", "variation": -1, "variation_orig": -1, "name": "Pirate Cove", "season": "fall"}, {"key": "IslandSouthEastCave", "variation": -1, "variation_orig": -1, "name": "Pirate Cove", "season": "winter"}, {"key": "IslandSecret", "variation": -1, "variation_orig": -1, "name": "Isola Zenzero secret location", "season": "spring"}, {"key": "IslandSecret", "variation": -1, "variation_orig": -1, "name": "Isola Zenzero secret location", "season": "summer"}, {"key": "IslandSecret", "variation": -1, "variation_orig": -1, "name": "Isola Zenzero secret location", "season": "fall"}, {"key": "IslandSecret", "variation": -1, "variation_orig": -1, "name": "Isola Zenzero secret location", "season": "winter"}]}, "269": {"en_name": "Midnight Carp", "name": "Carpa di mezzanotte", "time_ranges": [[2200, 2600]], "weather": ["sunny", "rainy"], "min_level": 12, "max_depth": 1, "spawn_multi": 0.33, "depth_multi": 0.1, "id": 269, "locations": [{"key": "Forest", "variation": 1, "variation_orig": 1, "name": "Foresta Linfabrace (pond)", "season": "fall"}, {"key": "Forest", "variation": 1, "variation_orig": 1, "name": "Foresta Linfabrace (pond)", "season": "winter"}, {"key": "Mountain", "variation": -1, "variation_orig": -1, "name": "Lago montano", "season": "fall"}, {"key": "Mountain", "variation": -1, "variation_orig": -1, "name": "Lago montano", "season": "winter"}, {"key": "IslandNorth", "variation": -1, "variation_orig": -1, "name": "Isola Zenzero north", "season": "spring"}, {"key": "IslandNorth", "variation": -1, "variation_orig": -1, "name": "Isola Zenzero north", "season": "summer"}, {"key": "IslandNorth", "variation": -1, "variation_orig": -1, "name": "Isola Zenzero north", "season": "fall"}, {"key": "IslandNorth", "variation": -1, "variation_orig": -1, "name": "Isola Zenzero north", "season": "winter"}, {"key": "IslandWest", "variation": 2, "variation_orig": 2, "name": "Isola Zenzero west (freshwater)", "season": "spring"}, {"key": "IslandWest", "variation": 2, "variation_orig": 2, "name": "Isola Zenzero west (freshwater)", "season": "summer"}, {"key": "IslandWest", "variation": 2, "variation_orig": 2, "name": "Isola Zenzero west (freshwater)", "season": "fall"}, {"key": "IslandWest", "variation": 2, "variation_orig": 2, "name": "Isola Zenzero west (freshwater)", "season": "winter"}]}, "698": {"en_name": "Sturgeon", "name": "Storione", "time_ranges": [[600, 1900]], "weather": ["sunny", "rainy"], "min_level": 12, "max_depth": 3, "spawn_multi": 0.35, "depth_multi": 0.2, "id": 698, "locations": [{"key": "Mountain", "variation": -1, "variation_orig": -1, "name": "Lago montano", "season": "summer"}, {"key": "Mountain", "variation": -1, "variation_orig": -1, "name": "Lago montano", "season": "winter"}, {"key": "Backwoods", "variation": -1, "variation_orig": -1, "name": "Boschi sul retro", "season": "summer"}, {"key": "Backwoods", "variation": -1, "variation_orig": -1, "name": "Boschi sul retro", "season": "winter"}]}, "699": {"en_name": "Tiger Trout", "name": "Trota tigre", "time_ranges": [[600, 1900]], "weather": ["sunny", "rainy"], "min_level": 10, "max_depth": 3, "spawn_multi": 0.2, "depth_multi": 0.1, "id": 699, "locations": [{"key": "Forest", "variation": 0, "variation_orig": 0, "name": "Foresta Linfabrace (river)", "season": "fall"}, {"key": "Forest", "variation": 0, "variation_orig": 0, "name": "Foresta Linfabrace (river)", "season": "winter"}, {"key": "Town", "variation": -1, "variation_orig": -1, "name": "Pelican Town", "season": "fall"}, {"key": "Town", "variation": -1, "variation_orig": -1, "name": "Pelican Town", "season": "winter"}]}, "700": {"en_name": "Bullhead", "name": "Scazzone", "time_ranges": [[600, 2600]], "weather": ["sunny", "rainy"], "min_level": 12, "max_depth": 2, "spawn_multi": 0.35, "depth_multi": 0.2, "id": 700, "locations": [{"key": "Mountain", "variation": -1, "variation_orig": -1, "name": "Lago montano", "season": "spring"}, {"key": "Mountain", "variation": -1, "variation_orig": -1, "name": "Lago montano", "season": "summer"}, {"key": "Mountain", "variation": -1, "variation_orig": -1, "name": "Lago montano", "season": "fall"}, {"key": "Mountain", "variation": -1, "variation_orig": -1, "name": "Lago montano", "season": "winter"}, {"key": "Backwoods", "variation": -1, "variation_orig": -1, "name": "Boschi sul retro", "season": "spring"}, {"key": "Backwoods", "variation": -1, "variation_orig": -1, "name": "Boschi sul retro", "season": "summer"}, {"key": "Backwoods", "variation": -1, "variation_orig": -1, "name": "Boschi sul retro", "season": "fall"}, {"key": "Backwoods", "variation": -1, "variation_orig": -1, "name": "Boschi sul retro", "season": "winter"}]}, "701": {"en_name": "Tilapia", "name": "Tilapia", "time_ranges": [[600, 1400]], "weather": ["sunny", "rainy"], "min_level": 11, "max_depth": 3, "spawn_multi": 0.4, "depth_multi": 0.2, "id": 701, "locations": [{"key": "Beach", "variation": -1, "variation_orig": -1, "name": "Spiaggia di Pelican", "season": "summer"}, {"key": "Beach", "variation": -1, "variation_orig": -1, "name": "Spiaggia di Pelican", "season": "fall"}, {"key": "IslandNorth", "variation": -1, "variation_orig": -1, "name": "Isola Zenzero north", "season": "spring"}, {"key": "IslandNorth", "variation": -1, "variation_orig": -1, "name": "Isola Zenzero north", "season": "summer"}, {"key": "IslandNorth", "variation": -1, "variation_orig": -1, "name": "Isola Zenzero north", "season": "fall"}, {"key": "IslandNorth", "variation": -1, "variation_orig": -1, "name": "Isola Zenzero north", "season": "winter"}, {"key": "IslandWest", "variation": 2, "variation_orig": 2, "name": "Isola Zenzero west (freshwater)", "season": "spring"}, {"key": "IslandWest", "variation": 2, "variation_orig": 2, "name": "Isola Zenzero west (freshwater)", "season": "summer"}, {"key": "IslandWest", "variation": 2, "variation_orig": 2, "name": "Isola Zenzero west (freshwater)", "season": "fall"}, {"key": "IslandWest", "variation": 2, "variation_orig": 2, "name": "Isola Zenzero west (freshwater)", "season": "winter"}]}, "702": {"en_name": "Chub", "name": "Cavedano", "time_ranges": [[600, 2600]], "weather": ["sunny", "rainy"], "min_level": 12, "max_depth": 1, "spawn_multi": 0.45, "depth_multi": 0.1, "id": 702, "locations": [{"key": "Forest", "variation": 0, "variation_orig": 0, "name": "Foresta Linfabrace (river)", "season": "spring"}, {"key": "Forest", "variation": 0, "variation_orig": 0, "name": "Foresta Linfabrace (river)", "season": "summer"}, {"key": "Forest", "variation": 0, "variation_orig": 0, "name": "Foresta Linfabrace (river)", "season": "fall"}, {"key": "Forest", "variation": 0, "variation_orig": 0, "name": "Foresta Linfabrace (river)", "season": "winter"}, {"key": "Mountain", "variation": -1, "variation_orig": -1, "name": "Lago montano", "season": "spring"}, {"key": "Mountain", "variation": -1, "variation_orig": -1, "name": "Lago montano", "season": "summer"}, {"key": "Mountain", "variation": -1, "variation_orig": -1, "name": "Lago montano", "season": "fall"}, {"key": "Mountain", "variation": -1, "variation_orig": -1, "name": "Lago montano", "season": "winter"}, {"key": "Backwoods", "variation": -1, "variation_orig": -1, "name": "Boschi sul retro", "season": "spring"}, {"key": "Backwoods", "variation": -1, "variation_orig": -1, "name": "Boschi sul retro", "season": "summer"}, {"key": "Backwoods", "variation": -1, "variation_orig": -1, "name": "Boschi sul retro", "season": "fall"}, {"key": "Backwoods", "variation": -1, "variation_orig": -1, "name": "Boschi sul retro", "season": "winter"}]}, "704": {"en_name": "Dorado", "name": "Dorado", "time_ranges": [[600, 1900]], "weather": ["sunny", "rainy"], "min_level": 24, "max_depth": 3, "spawn_multi": 0.15, "depth_multi": 0.1, "id": 704, "locations": [{"key": "Forest", "variation": 0, "variation_orig": 0, "name": "Foresta Linfabrace (river)", "season": "summer"}]}, "705": {"en_name": "Albacore", "name": "Alalonga", "time_ranges": [[600, 1100], [1800, 2600]], "weather": ["sunny", "rainy"], "min_level": 20, "max_depth": 3, "spawn_multi": 0.3, "depth_multi": 0.15, "id": 705, "locations": [{"key": "Beach", "variation": -1, "variation_orig": -1, "name": "Spiaggia di Pelican", "season": "fall"}, {"key": "Beach", "variation": -1, "variation_orig": -1, "name": "Spiaggia di Pelican", "season": "winter"}]}, "706": {"en_name": "Shad", "name": "Alosa", "time_ranges": [[900, 2600]], "weather": ["rainy"], "min_level": 20, "max_depth": 2, "spawn_multi": 0.35, "depth_multi": 0.2, "id": 706, "locations": [{"key": "Forest", "variation": 0, "variation_orig": 0, "name": "Foresta Linfabrace (river)", "season": "spring"}, {"key": "Forest", "variation": 0, "variation_orig": 0, "name": "Foresta Linfabrace (river)", "season": "summer"}, {"key": "Forest", "variation": 0, "variation_orig": 0, "name": "Foresta Linfabrace (river)", "season": "fall"}, {"key": "Town", "variation": -1, "variation_orig": -1, "name": "Pelican Town", "season": "spring"}, {"key": "Town", "variation": -1, "variation_orig": -1, "name": "Pelican Town", "season": "summer"}, {"key": "Town", "variation": -1, "variation_orig": -1, "name": "Pelican Town", "season": "fall"}]}, "707": {"en_name": "Lingcod", "name": "Ofiodonte", "time_ranges": [[600, 2600]], "weather": ["sunny", "rainy"], "min_level": 30, "max_depth": 3, "spawn_multi": 0.3, "depth_multi": 0.05, "id": 707, "locations": [{"key": "Forest", "variation": 0, "variation_orig": 0, "name": "Foresta Linfabrace (river)", "season": "winter"}, {"key": "Town", "variation": -1, "variation_orig": -1, "name": "Pelican Town", "season": "winter"}, {"key": "Mountain", "variation": -1, "variation_orig": -1, "name": "Lago montano", "season": "winter"}, {"key": "Backwoods", "variation": -1, "variation_orig": -1, "name": "Boschi sul retro", "season": "winter"}]}, "708": {"en_name": "Halibut", "name": "Ippoglosso", "time_ranges": [[600, 1100], [1900, 2600]], "weather": ["sunny", "rainy"], "min_level": 10, "max_depth": 3, "spawn_multi": 0.4, "depth_multi": 0.2, "id": 708, "locations": [{"key": "Beach", "variation": -1, "variation_orig": -1, "name": "Spiaggia di Pelican", "season": "spring"}, {"key": "Beach", "variation": -1, "variation_orig": -1, "name": "Spiaggia di Pelican", "season": "summer"}, {"key": "Beach", "variation": -1, "variation_orig": -1, "name": "Spiaggia di Pelican", "season": "winter"}, {"key": "IslandSecret", "variation": -1, "variation_orig": -1, "name": "Isola Zenzero secret location", "season": "spring"}, {"key": "IslandSecret", "variation": -1, "variation_orig": -1, "name": "Isola Zenzero secret location", "season": "summer"}, {"key": "IslandSecret", "variation": -1, "variation_orig": -1, "name": "Isola Zenzero secret location", "season": "fall"}, {"key": "IslandSecret", "variation": -1, "variation_orig": -1, "name": "Isola Zenzero secret location", "season": "winter"}]}, "734": {"en_name": "Woodskip", "name": "Saltaboschi", "time_ranges": [[600, 2600]], "weather": ["sunny", "rainy"], "min_level": 11, "max_depth": 3, "spawn_multi": 0.2, "depth_multi": 0.1, "id": 734, "locations": [{"key": "Woods", "variation": -1, "variation_orig": -1, "name": "Boschi segreti", "season": "spring"}, {"key": "Woods", "variation": -1, "variation_orig": -1, "name": "Boschi segreti", "season": "summer"}, {"key": "Woods", "variation": -1, "variation_orig": -1, "name": "Boschi segreti", "season": "fall"}, {"key": "Woods", "variation": -1, "variation_orig": -1, "name": "Boschi segreti", "season": "winter"}]}, "795": {"en_name": "Void Salmon", "name": "Salmone del vuoto", "time_ranges": [[600, 2600]], "weather": ["sunny", "rainy"], "min_level": 24, "max_depth": 2, "spawn_multi": 0.33, "depth_multi": 0.1, "id": 795, "locations": [{"key": "WitchSwamp", "variation": -1, "variation_orig": -1, "name": "Witch's Swamp", "season": "spring"}, {"key": "WitchSwamp", "variation": -1, "variation_orig": -1, "name": "Witch's Swamp", "season": "summer"}, {"key": "WitchSwamp", "variation": -1, "variation_orig": -1, "name": "Witch's Swamp", "season": "fall"}, {"key": "WitchSwamp", "variation": -1, "variation_orig": -1, "name": "Witch's Swamp", "season": "winter"}]}, "796": {"en_name": "Slimejack", "name": "Luccio melmoso", "time_ranges": [[600, 2600]], "weather": ["sunny", "rainy"], "min_level": 8, "max_depth": 3, "spawn_multi": 0.4, "depth_multi": 0.1, "id": 796, "locations": [{"key": "BugLand", "variation": -1, "variation_orig": -1, "name": "Mutant Bug Lair", "season": "spring"}, {"key": "BugLand", "variation": -1, "variation_orig": -1, "name": "Mutant Bug Lair", "season": "summer"}, {"key": "BugLand", "variation": -1, "variation_orig": -1, "name": "Mutant Bug Lair", "season": "fall"}, {"key": "BugLand", "variation": -1, "variation_orig": -1, "name": "Mutant Bug Lair", "season": "winter"}]}, "798": {"en_name": "Midnight Squid", "name": "Calamaro di mezzanotte", "time_ranges": [[600, 2600]], "weather": ["sunny", "rainy"], "min_level": 8, "max_depth": 3, "spawn_multi": 0.4, "depth_multi": 0.1, "id": 798}, "799": {"en_name": "Spook Fish", "name": "Pesce spettro", "time_ranges": [[600, 2600]], "weather": ["sunny", "rainy"], "min_level": 8, "max_depth": 3, "spawn_multi": 0.4, "depth_multi": 0.1, "id": 799}, "800": {"en_name": "Blobfish", "name": "Pesce blob", "time_ranges": [[600, 2600]], "weather": ["sunny", "rainy"], "min_level": 8, "max_depth": 3, "spawn_multi": 0.4, "depth_multi": 0.1, "id": 800}, "836": {"en_name": "Stingray", "name": "Razza", "time_ranges": [[600, 2600]], "weather": ["sunny", "rainy"], "min_level": 18, "max_depth": 4, "spawn_multi": 0.2, "depth_multi": 0.1, "id": 836, "locations": [{"key": "IslandSouthEastCave", "variation": -1, "variation_orig": -1, "name": "Pirate Cove", "season": "spring"}, {"key": "IslandSouthEastCave", "variation": -1, "variation_orig": -1, "name": "Pirate Cove", "season": "summer"}, {"key": "IslandSouthEastCave", "variation": -1, "variation_orig": -1, "name": "Pirate Cove", "season": "fall"}, {"key": "IslandSouthEastCave", "variation": -1, "variation_orig": -1, "name": "Pirate Cove", "season": "winter"}, {"key": "IslandSecret", "variation": -1, "variation_orig": -1, "name": "Isola Zenzero secret location", "season": "spring"}, {"key": "IslandSecret", "variation": -1, "variation_orig": -1, "name": "Isola Zenzero secret location", "season": "summer"}, {"key": "IslandSecret", "variation": -1, "variation_orig": -1, "name": "Isola Zenzero secret location", "season": "fall"}, {"key": "IslandSecret", "variation": -1, "variation_orig": -1, "name": "Isola Zenzero secret location", "season": "winter"}]}, "837": {"en_name": "Lionfish", "name": "Pesce scorpione", "time_ranges": [[600, 2600]], "weather": ["sunny", "rainy"], "min_level": 3, "max_depth": 3, "spawn_multi": 0.4, "depth_multi": 0.1, "id": 837, "locations": [{"key": "IslandSouth", "variation": -1, "variation_orig": -1, "name": "Isola Zenzero south", "season": "spring"}, {"key": "IslandSouth", "variation": -1, "variation_orig": -1, "name": "Isola Zenzero south", "season": "summer"}, {"key": "IslandSouth", "variation": -1, "variation_orig": -1, "name": "Isola Zenzero south", "season": "fall"}, {"key": "IslandSouth", "variation": -1, "variation_orig": -1, "name": "Isola Zenzero south", "season": "winter"}, {"key": "IslandWest", "variation": 1, "variation_orig": 1, "name": "Isola Zenzero west (ocean)", "season": "spring"}, {"key": "IslandWest", "variation": 1, "variation_orig": 1, "name": "Isola Zenzero west (ocean)", "season": "summer"}, {"key": "IslandWest", "variation": 1, "variation_orig": 1, "name": "Isola Zenzero west (ocean)", "season": "fall"}, {"key": "IslandWest", "variation": 1, "variation_orig": 1, "name": "Isola Zenzero west (ocean)", "season": "winter"}, {"key": "IslandSouthEast", "variation": -1, "variation_orig": -1, "name": "Isola Zenzero southeast", "season": "spring"}, {"key": "IslandSouthEast", "variation": -1, "variation_orig": -1, "name": "Isola Zenzero southeast", "season": "summer"}, {"key": "IslandSouthEast", "variation": -1, "variation_orig": -1, "name": "Isola Zenzero southeast", "season": "fall"}, {"key": "IslandSouthEast", "variation": -1, "variation_orig": -1, "name": "Isola Zenzero southeast", "season": "winter"}]}, "838": {"en_name": "Blue Discus", "name": "Pesce disco", "time_ranges": [[600, 2600]], "weather": ["sunny", "rainy"], "min_level": 2, "max_depth": 1, "spawn_multi": 0.25, "depth_multi": 0.1, "id": 838, "locations": [{"key": "IslandNorth", "variation": -1, "variation_orig": -1, "name": "Isola Zenzero north", "season": "spring"}, {"key": "IslandNorth", "variation": -1, "variation_orig": -1, "name": "Isola Zenzero north", "season": "summer"}, {"key": "IslandNorth", "variation": -1, "variation_orig": -1, "name": "Isola Zenzero north", "season": "fall"}, {"key": "IslandNorth", "variation": -1, "variation_orig": -1, "name": "Isola Zenzero north", "season": "winter"}, {"key": "IslandWest", "variation": 2, "variation_orig": 2, "name": "Isola Zenzero west (freshwater)", "season": "spring"}, {"key": "IslandWest", "variation": 2, "variation_orig": 2, "name": "Isola Zenzero west (freshwater)", "season": "summer"}, {"key": "IslandWest", "variation": 2, "variation_orig": 2, "name": "Isola Zenzero west (freshwater)", "season": "fall"}, {"key": "IslandWest", "variation": 2, "variation_orig": 2, "name": "Isola Zenzero west (freshwater)", "season": "winter"}]}, "898": {"en_name": "Son of Crimsonfish", "name": "Son of Crimsonfish", "time_ranges": [[600, 2000]], "weather": ["sunny", "rainy"], "min_level": 20, "max_depth": 4, "spawn_multi": 0.1, "depth_multi": 0.1, "id": 898}, "899": {"en_name": "Ms. Angler", "name": "Ms. Angler", "time_ranges": [[600, 2600]], "weather": ["sunny", "rainy"], "min_level": 18, "max_depth": 4, "spawn_multi": 0.05, "depth_multi": 0.1, "id": 899}, "900": {"en_name": "Legend II", "name": "Legend II", "time_ranges": [[600, 2000]], "weather": ["rainy"], "min_level": 50, "max_depth": 5, "spawn_multi": 0.0, "depth_multi": 0.1, "id": 900}, "901": {"en_name": "Radioactive Carp", "name": "Radioactive Carp", "time_ranges": [[600, 2600]], "weather": ["sunny", "rainy"], "min_level": 36, "max_depth": 5, "spawn_multi": 0.0, "depth_multi": 0.02, "id": 901}, "902": {"en_name": "Glacierfish Jr.", "name": "Glacierfish Jr.", "time_ranges": [[600, 2000]], "weather": ["sunny"], "min_level": 27, "max_depth": 5, "spawn_multi": 0.0, "depth_multi": 0.02, "id": 902}}, "location_names": {"UndergroundMine": {"-1": "Miniere"}, "Desert": {"-1": "Deserto di Calico"}, "Forest": {"0": "Foresta Linfabrace (river)", "1": "Foresta Linfabrace (pond)"}, "Town": {"-1": "Pelican Town"}, "Mountain": {"-1": "Lago montano"}, "Backwoods": {"-1": "Boschi sul retro"}, "Beach": {"-1": "Spiaggia di Pelican"}, "Woods": {"-1": "Boschi segreti"}, "Sewer": {"-1": "Fogne"}, "BugLand": {"-1": "Mutant Bug Lair"}, "WitchSwamp": {"-1": "Witch's Swamp"}, "IslandNorth": {"-1": "Isola Zenzero north"}, "IslandSouth": {"-1": "Isola Zenzero south"}, "IslandWest": {"1": "Isola Zenzero west (ocean)", "2": "Isola Zenzero west (freshwater)"}, "IslandSouthEast": {"-1": "Isola Zenzero southeast"}, "IslandSouthEastCave": {"-1": "Pirate Cove"}, "IslandSecret": {"-1": "Isola Zenzero secret location"}}}